README
setup.py
django_sprites.egg-info/PKG-INFO
django_sprites.egg-info/SOURCES.txt
django_sprites.egg-info/dependency_links.txt
django_sprites.egg-info/requires.txt
django_sprites.egg-info/top_level.txt
sprites/__init__.py
sprites/admin.py
sprites/middleware.py
sprites/models.py
sprites/tests.py
sprites/views.py