Metadata-Version: 1.0
Name: django-sprites
Version: 0.3.0
Summary: Django app models to handle image sprites to speed up page loads with multiple small images.
Home-page: https://github.com/johnfink8/django-sprites
Author: John Fink
Author-email: johnfink8@gmail.com
License: MIT
Keywords: django sprite image
Platform: UNKNOWN
Classifier: Development Status :: 3 - Alpha
Classifier: Framework :: Django
Classifier: Intended Audience :: Developers
Classifier: License :: OSI Approved :: MIT License
Classifier: Topic :: Internet :: WWW/HTTP :: WSGI
